README.txt
setup.cfg
setup.py
docs/HISTORY.txt
raptus/__init__.py
raptus.workflownotificationtemplates.egg-info/PKG-INFO
raptus.workflownotificationtemplates.egg-info/SOURCES.txt
raptus.workflownotificationtemplates.egg-info/dependency_links.txt
raptus.workflownotificationtemplates.egg-info/entry_points.txt
raptus.workflownotificationtemplates.egg-info/namespace_packages.txt
raptus.workflownotificationtemplates.egg-info/not-zip-safe
raptus.workflownotificationtemplates.egg-info/requires.txt
raptus.workflownotificationtemplates.egg-info/top_level.txt
raptus/workflownotificationtemplates/__init__.py
raptus/workflownotificationtemplates/adapter.py
raptus/workflownotificationtemplates/configure.zcml
raptus/workflownotificationtemplates/interfaces.py
raptus/workflownotificationtemplates/Extensions/Install.py
raptus/workflownotificationtemplates/Extensions/__init__.py
raptus/workflownotificationtemplates/browser/__init__.py
raptus/workflownotificationtemplates/browser/configlet.pt
raptus/workflownotificationtemplates/browser/configlet.py
raptus/workflownotificationtemplates/browser/configure.zcml
raptus/workflownotificationtemplates/browser/icon.gif
raptus/workflownotificationtemplates/browser/vocabulary.py
raptus/workflownotificationtemplates/i18n/plone-raptus.workflownotificationtemplates-de.po
raptus/workflownotificationtemplates/i18n/plone-raptus.workflownotificationtemplates.pot
raptus/workflownotificationtemplates/i18n/raptus.workflownotificationtemplates-de.po
raptus/workflownotificationtemplates/i18n/raptus.workflownotificationtemplates.pot
raptus/workflownotificationtemplates/profiles/default/actionicons.xml
raptus/workflownotificationtemplates/profiles/default/controlpanel.xml
raptus/workflownotificationtemplates/profiles/default/metadata.xml
raptus/workflownotificationtemplates/profiles/uninstall/controlpanel.xml