Metadata-Version: 1.0
Name: raptus.workflownotificationtemplates
Version: 0.1
Summary: Provides a configlet to write notification templates ttw
Home-page: http://plone.org/products/raptus.workflownotificationtemplates
Author: Raptus AG
Author-email: skaeser@raptus.com
License: GPL
Keywords: plone notification
Platform: UNKNOWN
Classifier: Programming Language :: Python
Classifier: Topic :: Software Development :: Libraries :: Python Modules
